<absences>
    <absence>
        <idAbsence>1</idAbsence>
        <motifAbsence>Congé annuel</motifAbsence>
        <nombreDeJours>5</nombreDeJours>
        <dateAbsence>2021-05-10</dateAbsence>
        <idEmploye>1</idEmploye>
    </absence>
    <absence>
        <idAbsence>2</idAbsence>
        <motifAbsence>Maladie</motifAbsence>
        <nombreDeJours>2</nombreDeJours>
        <dateAbsence>2021-02-15</dateAbsence>
        <idEmploye>2</idEmploye>
    </absence>
    <absence>
        <idAbsence>3</idAbsence>
        <motifAbsence>Congé sans solde</motifAbsence>
        <nombreDeJours>15</nombreDeJours>
        <dateAbsence>2022-07-10</dateAbsence>
        <idEmploye>6</idEmploye>
    </absence>
    <absence>
        <idAbsence>4</idAbsence>
        <motifAbsence>Congé maladie enfant</motifAbsence>
        <nombreDeJours>3</nombreDeJours>
        <dateAbsence>2021-11-12</dateAbsence>
        <idEmploye>7</idEmploye>
    </absence>
    <absence>
        <idAbsence>8</idAbsence>
        <motifAbsence>Congé maternité</motifAbsence>
        <nombreDeJours>90</nombreDeJours>
        <dateAbsence>2021-09-05</dateAbsence>
        <idEmploye>8</idEmploye>
    </absence>
    <absence>
        <idAbsence>5</idAbsence>
        <motifAbsence>Formation</motifAbsence>
        <nombreDeJours>2</nombreDeJours>
        <dateAbsence>2021-10-20</dateAbsence>
        <idEmploye>3</idEmploye>
    </absence>
    <absence>
        <idAbsence>6</idAbsence>
        <motifAbsence>Congé annuel</motifAbsence>
        <nombreDeJours>8</nombreDeJours>
        <dateAbsence>2021-10-01</dateAbsence>
        <idEmploye>10</idEmploye>
    </absence>
    <absence>
        <idAbsence>7</idAbsence>
        <motifAbsence>Formation</motifAbsence>
        <nombreDeJours>6</nombreDeJours>
        <dateAbsence>2022-12-20</dateAbsence>
        <idEmploye>7</idEmploye>
    </absence>
</absences>

